{
	"version": "5.3.2",
	"version_code" : 1,
	"updatename": "EasyReader_5.3.2.apk",
	"updatefile": "https://play.google.com/store/apps/details?id=tw.clotai.easyreader",
	"changelog": "
<b>變更紀錄:</b><p>
<p><strong>v 5.3.2</strong><br />+ 更新網站資料庫至 109<br />+ 調整廣告顯示部份<br />+ 新增語言設定，可選擇使用系統設定<br /><strong>BUGS</strong><br />- 修正部份強制關閉的問題</p>
<p>
下載網址:<br/>
<a href='https://app.box.com/s/k7yzgbvqw3bi77ai9a718sewl60v0c0u'>Box</a><br/>
<a href='https://pan.baidu.com/s/1sfvJkvHVxbMNjMBZtKJZ-w'>百度雲</a>
"
}
